{
  "project_info": {
    "project_number": "946063971515",
    "firebase_url": "https://easypet-3903f-default-rtdb.europe-west1.firebasedatabase.app",
    "project_id": "easypet-3903f",
    "storage_bucket": "easypet-3903f.firebasestorage.app"
  },
  "client": [
    {
      "client_info": {
        "mobilesdk_app_id": "1:946063971515:android:c0d6229b593c5fc027059e",
        "android_client_info": {
          "package_name": "com.easypets"
        }
      },
      "oauth_client": [
        {
          "client_id": "946063971515-b14nha6eo1vfsj9j79arqfu534ugjlos.apps.googleusercontent.com",
          "client_type": 1,
          "android_info": {
            "package_name": "com.easypets",
            "certificate_hash": "a2c207fb7c4aee3c2d844bdf45df34b6323672bf"
          }
        },
        {
          "client_id": "946063971515-jrvjpri2nf2as4hn1qo8t8tbjrlqu3e0.apps.googleusercontent.com",
          "client_type": 1,
          "android_info": {
            "package_name": "com.easypets",
            "certificate_hash": "f800f3195456140f509120966951026070de7ac9"
          }
        },
        {
          "client_id": "946063971515-k1utkhhrbogefnajgs4olokqbfod0obf.apps.googleusercontent.com",
          "client_type": 3
        }
      ],
      "api_key": [
        {
          "current_key": "AIzaSyBVDwvBEYvXCehwWaYFBLfdsPYrvhaVxbc"
        }
      ],
      "services": {
        "appinvite_service": {
          "other_platform_oauth_client": [
            {
              "client_id": "946063971515-k1utkhhrbogefnajgs4olokqbfod0obf.apps.googleusercontent.com",
              "client_type": 3
            }
          ]
        }
      }
    }
  ],
  "configuration_version": "1"
}